{
  "sections": [
    {
      "section": "overview",
      "files": [
        {
          "title": "Kubernetes 101",
          "file": "Readme.md"
        }
      ]
    },
    {
      "section": "guides",
      "files": [
        {
          "title": "Ingress and Routing",
          "file": "ingress.md"
        },
        {
          "title": "Service Types in Kubernetes",
          "file": "services.md"
        },
        {
          "title": "Smoke Tests",
          "file": "smoke.md"
        },
        {
          "title": "Persistent Storage",
          "file": "storage.md"
        },
        {
          "title": "Persistent Storage2",
          "file": "https://raw.githubusercontent.com/oracle/cloudnative/master/infrastructure/database/Persistent-storage/persistentStorage.md"
        }
      ]
    }
  ]
}
